{
    "defaultEnv": {"ENV": "MIGRATION_ENV"},
    "dev": {
        "driver": "pg",
        "user": "postgres",
        "password": "root",
        "host": "localhost",
        "database": "vision",
        "port": "5432"
    },
	"test": {
        "driver": "pg",
        "user": "xdhkecusyqwuwf",
        "password": "48d8e44f007b7dbd3085427190da1181dccffc031495d1581d88ec3f65fb5164",
        "host": "ec2-44-213-151-75.compute-1.amazonaws.com",
        "database": "dasfhu24l1rlke",
        "port": "5432",
		"ssl": {
      		"rejectUnauthorized": false
    	}
    },
    "prod": {
        "driver": "pg",
        "user": "izpxxbdgahciaf",
        "password": "df2464ba0e80e7adb8339dc26d38010b19d2803b525e815c339257307df89f78",
        "host": "ec2-44-214-132-149.compute-1.amazonaws.com",
        "database": "d9m2i8pnj98amd",
        "port": "5432",
        "ssl": {
      		"rejectUnauthorized": false
    	}
    }
}